[
{"gender":"F","firstName":"Rachel","lastName":"Brown","age":71},
{"gender":"M","firstName":"Tom","lastName":"Jones","age":24},
{"gender":"F","firstName":"Michelle","lastName":"Doe","age":75},
{"gender":"F","firstName":"Emma","lastName":"Smith","age":31},
{"gender":"F","firstName":"Rachel","lastName":"Doe","age":68},
{"gender":"F","firstName":"Olivia","lastName":"Brown","age":19},
{"gender":"M","firstName":"John","lastName":"Jones","age":38},
{"gender":"F","firstName":"Emma","lastName":"Pitt","age":31},
{"gender":"F","firstName":"Olivia","lastName":"Brown","age":34},
{"gender":"F","firstName":"Emily","lastName":"Brown","age":60},
{"gender":"M","firstName":"Tom","lastName":"Brown","age":68},
{"gender":"M","firstName":"Michael","lastName":"Pitt","age":38},
{"gender":"M","firstName":"Joe","lastName":"Doe","age":54},
{"gender":"F","firstName":"Rachel","lastName":"Doe","age":23},
{"gender":"M","firstName":"Michael","lastName":"Jones","age":65},
{"gender":"M","firstName":"Tom","lastName":"Pitt","age":32},
{"gender":"M","firstName":"Joe","lastName":"Jones","age":26},
{"gender":"M","firstName":"Michael","lastName":"Doe","age":51},
{"gender":"M","firstName":"John","lastName":"Jones","age":44},
{"gender":"F","firstName":"Olivia","lastName":"Pitt","age":30}
]